minify_html_onepass-0.18.0.dist-info/METADATA
minify_html_onepass-0.18.0.dist-info/WHEEL
minify_html_onepass/__init__.py
minify_html_onepass/__init__.pyi
minify_html_onepass/minify_html_onepass.cpython-313-x86_64-linux-gnu.so
minify_html_onepass/py.typed
minify_html_onepass-0.18.0.dist-info/RECORD
