Metadata-Version: 2.4
Name: minify_html_onepass
Version: 0.18.0
Summary: Even faster version of minify-html
Home-Page: https://github.com/wilsonzlin/minify-html
Author: Wilson Lin <code@wilsonl.in>
Author-email: Wilson Lin <code@wilsonl.in>
License: MIT
Project-URL: Source Code, https://github.com/wilsonzlin/minify-html.git
